MANIFEST.in
README.rst
setup.py
python_paris/__init__.py
python_paris/cluster_cut_slicer.py
python_paris/distance_slicer.py
python_paris/heterogeneous_cut_slicer.py
python_paris/homogeneous_cut_slicer.py
python_paris/paris.py
python_paris.egg-info/PKG-INFO
python_paris.egg-info/SOURCES.txt
python_paris.egg-info/dependency_links.txt
python_paris.egg-info/not-zip-safe
python_paris.egg-info/requires.txt
python_paris.egg-info/top_level.txt